{
  "graph_seeds": [
    0,
    1,
    2
  ],
  "twod": {
    "SBM-Clean": {
      "louvain": {
        "nmi": {
          "mean": 1.0,
          "hr": 0.0,
          "n": 3
        },
        "se2d": {
          "mean": 6.0261,
          "hr": 0.0081,
          "n": 3
        }
      },
      "leiden": {
        "nmi": {
          "mean": 1.0,
          "hr": 0.0,
          "n": 3
        },
        "se2d": {
          "mean": 6.0261,
          "hr": 0.0081,
          "n": 3
        }
      },
      "infomap": {
        "nmi": {
          "mean": 1.0,
          "hr": 0.0,
          "n": 3
        },
        "se2d": {
          "mean": 6.0261,
          "hr": 0.0081,
          "n": 3
        }
      },
      "codeseg": {
        "nmi": {
          "mean": 0.4734,
          "hr": 0.0525,
          "n": 3
        },
        "se2d": {
          "mean": 6.2852,
          "hr": 0.0273,
          "n": 3
        }
      },
      "se_louvain": {
        "nmi": {
          "mean": 0.7694,
          "hr": 0.0068,
          "n": 3
        },
        "se2d": {
          "mean": 5.9767,
          "hr": 0.0162,
          "n": 3
        }
      }
    },
    "SBM-Noisy": {
      "louvain": {
        "nmi": {
          "mean": 0.0804,
          "hr": 0.024,
          "n": 3
        },
        "se2d": {
          "mean": 6.1865,
          "hr": 0.0142,
          "n": 3
        }
      },
      "leiden": {
        "nmi": {
          "mean": 0.0897,
          "hr": 0.0107,
          "n": 3
        },
        "se2d": {
          "mean": 6.1836,
          "hr": 0.0161,
          "n": 3
        }
      },
      "infomap": {
        "nmi": {
          "mean": 0.0,
          "hr": 0.0,
          "n": 3
        },
        "se2d": {
          "mean": 7.1849,
          "hr": 0.0027,
          "n": 3
        }
      },
      "codeseg": {
        "nmi": {
          "mean": 0.2182,
          "hr": 0.0119,
          "n": 3
        },
        "se2d": {
          "mean": 6.5273,
          "hr": 0.0192,
          "n": 3
        }
      },
      "se_louvain": {
        "nmi": {
          "mean": 0.1316,
          "hr": 0.0059,
          "n": 3
        },
        "se2d": {
          "mean": 6.1725,
          "hr": 0.0099,
          "n": 3
        }
      }
    },
    "LFR-mu0.1": {
      "louvain": {
        "nmi": {
          "mean": 1.0,
          "hr": 0.0,
          "n": 3
        },
        "se2d": {
          "mean": 4.9021,
          "hr": 0.1951,
          "n": 3
        }
      },
      "leiden": {
        "nmi": {
          "mean": 1.0,
          "hr": 0.0,
          "n": 3
        },
        "se2d": {
          "mean": 4.9021,
          "hr": 0.1951,
          "n": 3
        }
      },
      "infomap": {
        "nmi": {
          "mean": 1.0,
          "hr": 0.0,
          "n": 3
        },
        "se2d": {
          "mean": 4.9021,
          "hr": 0.1951,
          "n": 3
        }
      },
      "codeseg": {
        "nmi": {
          "mean": 0.8948,
          "hr": 0.0849,
          "n": 3
        },
        "se2d": {
          "mean": 5.2119,
          "hr": 0.4279,
          "n": 3
        }
      },
      "se_louvain": {
        "nmi": {
          "mean": 1.0,
          "hr": 0.0,
          "n": 3
        },
        "se2d": {
          "mean": 4.9021,
          "hr": 0.1951,
          "n": 3
        }
      }
    },
    "LFR-mu0.3": {
      "louvain": {
        "nmi": {
          "mean": 0.9637,
          "hr": 0.0189,
          "n": 3
        },
        "se2d": {
          "mean": 5.6546,
          "hr": 0.1083,
          "n": 3
        }
      },
      "leiden": {
        "nmi": {
          "mean": 0.9576,
          "hr": 0.0176,
          "n": 3
        },
        "se2d": {
          "mean": 5.6846,
          "hr": 0.1279,
          "n": 3
        }
      },
      "infomap": {
        "nmi": {
          "mean": 0.9218,
          "hr": 0.0589,
          "n": 3
        },
        "se2d": {
          "mean": 5.737,
          "hr": 0.2179,
          "n": 3
        }
      },
      "codeseg": {
        "nmi": {
          "mean": 0.7148,
          "hr": 0.0844,
          "n": 3
        },
        "se2d": {
          "mean": 6.0531,
          "hr": 0.1481,
          "n": 3
        }
      },
      "se_louvain": {
        "nmi": {
          "mean": 0.9439,
          "hr": 0.0653,
          "n": 3
        },
        "se2d": {
          "mean": 5.6432,
          "hr": 0.1171,
          "n": 3
        }
      }
    },
    "LFR-mu0.5": {
      "louvain": {
        "nmi": {
          "mean": 0.2909,
          "hr": 0.0992,
          "n": 3
        },
        "se2d": {
          "mean": 6.1708,
          "hr": 0.006,
          "n": 3
        }
      },
      "leiden": {
        "nmi": {
          "mean": 0.2815,
          "hr": 0.0992,
          "n": 3
        },
        "se2d": {
          "mean": 6.138,
          "hr": 0.0196,
          "n": 3
        }
      },
      "infomap": {
        "nmi": {
          "mean": 0.0,
          "hr": 0.0,
          "n": 3
        },
        "se2d": {
          "mean": 7.1472,
          "hr": 0.0076,
          "n": 3
        }
      },
      "codeseg": {
        "nmi": {
          "mean": 0.4264,
          "hr": 0.035,
          "n": 3
        },
        "se2d": {
          "mean": 6.4781,
          "hr": 0.0525,
          "n": 3
        }
      },
      "se_louvain": {
        "nmi": {
          "mean": 0.4025,
          "hr": 0.1101,
          "n": 3
        },
        "se2d": {
          "mean": 6.1175,
          "hr": 0.0232,
          "n": 3
        }
      }
    }
  },
  "hier": {
    "SBM-Clean": {
      "se_hier": {
        "hd_se": {
          "mean": 5.0377,
          "hr": 0.0117,
          "n": 3
        }
      },
      "se_agglomerative": {
        "hd_se": {
          "mean": 5.3209,
          "hr": 0.0112,
          "n": 3
        }
      },
      "paris": {
        "hd_se": {
          "mean": 5.0422,
          "hr": 0.0145,
          "n": 3
        }
      }
    },
    "SBM-Noisy": {
      "se_hier": {
        "hd_se": {
          "mean": 5.3479,
          "hr": 0.008,
          "n": 3
        }
      },
      "se_agglomerative": {
        "hd_se": {
          "mean": 5.4511,
          "hr": 0.0233,
          "n": 3
        }
      },
      "paris": {
        "hd_se": {
          "mean": 5.3479,
          "hr": 0.008,
          "n": 3
        }
      }
    },
    "LFR-mu0.1": {
      "se_hier": {
        "hd_se": {
          "mean": 3.982,
          "hr": 0.1658,
          "n": 3
        }
      },
      "se_agglomerative": {
        "hd_se": {
          "mean": 4.2106,
          "hr": 0.182,
          "n": 3
        }
      },
      "paris": {
        "hd_se": {
          "mean": 3.9839,
          "hr": 0.1686,
          "n": 3
        }
      }
    },
    "LFR-mu0.3": {
      "se_hier": {
        "hd_se": {
          "mean": 4.9509,
          "hr": 0.104,
          "n": 3
        }
      },
      "se_agglomerative": {
        "hd_se": {
          "mean": 5.0014,
          "hr": 0.1361,
          "n": 3
        }
      },
      "paris": {
        "hd_se": {
          "mean": 4.9958,
          "hr": 0.0901,
          "n": 3
        }
      }
    },
    "LFR-mu0.5": {
      "se_hier": {
        "hd_se": {
          "mean": 5.3627,
          "hr": 0.0078,
          "n": 3
        }
      },
      "se_agglomerative": {
        "hd_se": {
          "mean": 5.4603,
          "hr": 0.0324,
          "n": 3
        }
      },
      "paris": {
        "hd_se": {
          "mean": 5.3627,
          "hr": 0.0078,
          "n": 3
        }
      }
    }
  }
}